n3/__init__.py
n3/node/__init__.py
n3/node/data.py
n3/node/exec.py
n3/node/extern.py
n3/node/node.py
n3/node/optim.py
n3/std/builtins/__init__.py
n3/std/builtins/assert_shape.py
n3/std/builtins/concat.py
n3/std/builtins/to_linear.py
n3/std/builtins/transform.py
n3/std/data/mnist.n3
n3/std/data/mnist.py
n3/std/exec/image_classification.n3
n3/std/exec/image_classification.py
n3/std/models/vision/le_net5.n3
n3/std/models/vision/vgg.n3
n3/std/nn/activation/dropout.n3
n3/std/nn/activation/dropout.py
n3/std/nn/activation/relu.n3
n3/std/nn/activation/relu.py
n3/std/nn/activation/softmax.n3
n3/std/nn/activation/softmax.py
n3/std/nn/conv/batch_norm2d.n3
n3/std/nn/conv/batch_norm2d.py
n3/std/nn/conv/conv2d.n3
n3/std/nn/conv/conv2d.py
n3/std/nn/conv/max_pool2d.n3
n3/std/nn/conv/max_pool2d.py
n3/std/nn/linear/linear.n3
n3/std/nn/linear/linear.py
n3/std/nn/loss/cross_entropy.n3
n3/std/nn/loss/cross_entropy.py
n3/std/optim/adam.n3
n3/std/optim/adam.py
n3/util/__init__.py
n3/util/args.py
n3/util/dirs.py
n3/util/out.py
n3/writer/__init__.py
n3/writer/epoch.py
n3/writer/exec.py
n3-0.2.0.dist-info/LICENSE
n3-0.2.0.dist-info/METADATA
n3-0.2.0.dist-info/WHEEL
n3-0.2.0.dist-info/entry_points.txt
n3-0.2.0.dist-info/top_level.txt
n3-0.2.0.dist-info/RECORD
