Metadata-Version: 2.1
Name: n3
Version: 0.2.0
Summary: Nerual Network Notation
Home-page: https://github.com/kerryeon/n3
Author: Ho Kim
Author-email: ho.kim@gnu.ac.kr
Maintainer: Ho Kim
Maintainer-email: ho.kim@gnu.ac.kr
License: MIT
Platform: UNKNOWN
Requires-Dist: inflection
Requires-Dist: torch
Requires-Dist: torchvision
Requires-Dist: tensorboard
Requires-Dist: tensorboardX
Requires-Dist: tqdm
